CONTRIBUTORS.rst
MANIFEST.in
README.rst
setup.py
docs/handlers_ext.py
docs/make.bat
docs/source/apis.rst
docs/source/conf.py
docs/source/examples.rst
docs/source/extending.rst
docs/source/index.rst
docs/source/monkey.png
vaurien/__init__.py
vaurien/_pool.py
vaurien/config.py
vaurien/metaserver.py
vaurien/proxy.py
vaurien/run.py
vaurien/util.py
vaurien/web-requirements.txt
vaurien/webserver.py
vaurien.egg-info/PKG-INFO
vaurien.egg-info/SOURCES.txt
vaurien.egg-info/dependency_links.txt
vaurien.egg-info/entry_points.txt
vaurien.egg-info/not-zip-safe
vaurien.egg-info/requires.txt
vaurien.egg-info/top_level.txt
vaurien/behaviors/__init__.py
vaurien/behaviors/blackout.py
vaurien/behaviors/delay.py
vaurien/behaviors/dummy.py
vaurien/behaviors/error.py
vaurien/behaviors/hang.py
vaurien/behaviors/transient.py
vaurien/protocols/__init__.py
vaurien/protocols/base.py
vaurien/protocols/http.py
vaurien/protocols/memcache.py
vaurien/protocols/mysql.py
vaurien/protocols/redis.py
vaurien/protocols/smtp.py
vaurien/protocols/tcp.py
vaurien/tests/__init__.py
vaurien/tests/support.py
vaurien/tests/test_client.py
vaurien/tests/test_config.py
vaurien/tests/test_http_proxy.py
vaurien/tests/test_http_server.py
vaurien/tests/test_proxy.py
vaurien/tests/test_util.py
vaurien/tests/util.py