Metadata-Version: 1.1
Name: vaurien
Version: 1.9
Summary: TCP Chaos Proxy
Home-page: UNKNOWN
Author: Mozilla Foundation & contributors
Author-email: services-dev@lists.mozila.org
License: APLv2
Platform: UNKNOWN
Classifier: Programming Language :: Python
Classifier: License :: OSI Approved :: Apache Software License
Classifier: Development Status :: 1 - Planning
